{
  "timestamp": "2026-02-25T00:00:00+00:00",
  "date": "2026-02-25",
  "factor_weights": {
    "f_momentum_30d": 0.35,
    "f_momentum_7d": 0.25,
    "f_ath_drawdown": -0.2
  },
  "coins": [
    {
      "symbol": "INJ",
      "price": 3.2441368396183003,
      "market_cap": null,
      "f_momentum_30d": -0.2786755970473605,
      "f_momentum_7d": 0.11207512345502815,
      "f_ath_drawdown": -0.4244054342803087,
      "f_volume_turnover": null,
      "f_funding_rate": null,
      "f_tvl_mcap": null,
      "f_dev_activity": null,
      "f_onchain_activity": null,
      "f_narrative_heat": null,
      "f_market_cap_size": null,
      "composite_score": 0.0192
    },
    {
      "symbol": "HBAR",
      "price": 0.09396266857345675,
      "market_cap": null,
      "f_momentum_30d": -0.12410882413031887,
      "f_momentum_7d": -0.24148879381401492,
      "f_ath_drawdown": -0.36126862178033464,
      "f_volume_turnover": null,
      "f_funding_rate": null,
      "f_tvl_mcap": null,
      "f_dev_activity": null,
      "f_onchain_activity": null,
      "f_narrative_heat": null,
      "f_market_cap_size": null,
      "composite_score": -0.0394
    },
    {
      "symbol": "ATOM",
      "price": 2.105781688261444,
      "market_cap": null,
      "f_momentum_30d": -0.08722019959474218,
      "f_momentum_7d": -0.24699539766589623,
      "f_ath_drawdown": -0.1736418227656144,
      "f_volume_turnover": null,
      "f_funding_rate": null,
      "f_tvl_mcap": null,
      "f_dev_activity": null,
      "f_onchain_activity": null,
      "f_narrative_heat": null,
      "f_market_cap_size": null,
      "composite_score": -0.0719
    },
    {
      "symbol": "MKR",
      "price": 1471.3906232235981,
      "market_cap": null,
      "f_momentum_30d": -0.07114601497182885,
      "f_momentum_7d": -0.22261962925569712,
      "f_ath_drawdown": -0.11199761225844497,
      "f_volume_turnover": null,
      "f_funding_rate": null,
      "f_tvl_mcap": null,
      "f_dev_activity": null,
      "f_onchain_activity": null,
      "f_narrative_heat": null,
      "f_market_cap_size": null,
      "composite_score": -0.0727
    },
    {
      "symbol": "RNDR",
      "price": 1.3645139990358217,
      "market_cap": null,
      "f_momentum_30d": -0.31177506972422275,
      "f_momentum_7d": -0.21760990637393354,
      "f_ath_drawdown": -0.4758883476266189,
      "f_volume_turnover": null,
      "f_funding_rate": null,
      "f_tvl_mcap": null,
      "f_dev_activity": null,
      "f_onchain_activity": null,
      "f_narrative_heat": null,
      "f_market_cap_size": null,
      "composite_score": -0.0854
    },
    {
      "symbol": "ETC",
      "price": 8.20577800867655,
      "market_cap": null,
      "f_momentum_30d": -0.28388760588846607,
      "f_momentum_7d": -0.22552404976487914,
      "f_ath_drawdown": -0.3618092835608375,
      "f_volume_turnover": null,
      "f_funding_rate": null,
      "f_tvl_mcap": null,
      "f_dev_activity": null,
      "f_onchain_activity": null,
      "f_narrative_heat": null,
      "f_market_cap_size": null,
      "composite_score": -0.1042
    },
    {
      "symbol": "LTC",
      "price": 51.01799095269859,
      "market_cap": null,
      "f_momentum_30d": -0.2489348319119063,
      "f_momentum_7d": -0.2493007828951773,
      "f_ath_drawdown": -0.31838340443855395,
      "f_volume_turnover": null,
      "f_funding_rate": null,
      "f_tvl_mcap": null,
      "f_dev_activity": null,
      "f_onchain_activity": null,
      "f_narrative_heat": null,
      "f_market_cap_size": null,
      "composite_score": -0.1072
    },
    {
      "symbol": "NEAR",
      "price": 0.9758274853588593,
      "market_cap": null,
      "f_momentum_30d": -0.34810939581107636,
      "f_momentum_7d": -0.24786499000175222,
      "f_ath_drawdown": -0.47437285792657685,
      "f_volume_turnover": null,
      "f_funding_rate": null,
      "f_tvl_mcap": null,
      "f_dev_activity": null,
      "f_onchain_activity": null,
      "f_narrative_heat": null,
      "f_market_cap_size": null,
      "composite_score": -0.1112
    },
    {
      "symbol": "UNI",
      "price": 3.3244784068762137,
      "market_cap": null,
      "f_momentum_30d": -0.311286554234441,
      "f_momentum_7d": -0.24148883220948886,
      "f_ath_drawdown": -0.39598695015330626,
      "f_volume_turnover": null,
      "f_funding_rate": null,
      "f_tvl_mcap": null,
      "f_dev_activity": null,
      "f_onchain_activity": null,
      "f_narrative_heat": null,
      "f_market_cap_size": null,
      "composite_score": -0.1127
    },
    {
      "symbol": "AAVE",
      "price": 112.5358746038041,
      "market_cap": null,
      "f_momentum_30d": -0.27299750890689944,
      "f_momentum_7d": -0.3720884953310168,
      "f_ath_drawdown": -0.4506851712745616,
      "f_volume_turnover": null,
      "f_funding_rate": null,
      "f_tvl_mcap": null,
      "f_dev_activity": null,
      "f_onchain_activity": null,
      "f_narrative_heat": null,
      "f_market_cap_size": null,
      "composite_score": -0.123
    },
    {
      "symbol": "FIL",
      "price": 0.8832588725363149,
      "market_cap": null,
      "f_momentum_30d": -0.3219905616583349,
      "f_momentum_7d": -0.30604068883916036,
      "f_ath_drawdown": -0.44542595977468985,
      "f_volume_turnover": null,
      "f_funding_rate": null,
      "f_tvl_mcap": null,
      "f_dev_activity": null,
      "f_onchain_activity": null,
      "f_narrative_heat": null,
      "f_market_cap_size": null,
      "composite_score": -0.1252
    },
    {
      "symbol": "XLM",
      "price": 0.15011112691568082,
      "market_cap": null,
      "f_momentum_30d": -0.28492956855463036,
      "f_momentum_7d": -0.36226656601568463,
      "f_ath_drawdown": -0.34698136897125714,
      "f_volume_turnover": null,
      "f_funding_rate": null,
      "f_tvl_mcap": null,
      "f_dev_activity": null,
      "f_onchain_activity": null,
      "f_narrative_heat": null,
      "f_market_cap_size": null,
      "composite_score": -0.1511
    },
    {
      "symbol": "SUI",
      "price": 0.8600130965258385,
      "market_cap": null,
      "f_momentum_30d": -0.41599054929623835,
      "f_momentum_7d": -0.42373203112124164,
      "f_ath_drawdown": -0.5570787532165009,
      "f_volume_turnover": null,
      "f_funding_rate": null,
      "f_tvl_mcap": null,
      "f_dev_activity": null,
      "f_onchain_activity": null,
      "f_narrative_heat": null,
      "f_market_cap_size": null,
      "composite_score": -0.1751
    },
    {
      "symbol": "BCH",
      "price": 486.1753619970622,
      "market_cap": null,
      "f_momentum_30d": -0.17823704652662903,
      "f_momentum_7d": -0.47201352953921244,
      "f_ath_drawdown": -0.1887380498644114,
      "f_volume_turnover": null,
      "f_funding_rate": null,
      "f_tvl_mcap": null,
      "f_dev_activity": null,
      "f_onchain_activity": null,
      "f_narrative_heat": null,
      "f_market_cap_size": null,
      "composite_score": -0.1783
    },
    {
      "symbol": "LDO",
      "price": 0.29664813189351413,
      "market_cap": null,
      "f_momentum_30d": -0.424433702209029,
      "f_momentum_7d": -0.4537835345767567,
      "f_ath_drawdown": -0.5561227740205898,
      "f_volume_turnover": null,
      "f_funding_rate": null,
      "f_tvl_mcap": null,
      "f_dev_activity": null,
      "f_onchain_activity": null,
      "f_narrative_heat": null,
      "f_market_cap_size": null,
      "composite_score": -0.1885
    },
    {
      "symbol": "APT",
      "price": 0.8104670478178008,
      "market_cap": null,
      "f_momentum_30d": -0.4736201470748525,
      "f_momentum_7d": -0.4310362155085401,
      "f_ath_drawdown": -0.5879247407702936,
      "f_volume_turnover": null,
      "f_funding_rate": null,
      "f_tvl_mcap": null,
      "f_dev_activity": null,
      "f_onchain_activity": null,
      "f_narrative_heat": null,
      "f_market_cap_size": null,
      "composite_score": -0.1949
    },
    {
      "symbol": "ARB",
      "price": 0.0928826873854445,
      "market_cap": null,
      "f_momentum_30d": -0.4679577657318086,
      "f_momentum_7d": -0.6416308097312892,
      "f_ath_drawdown": -0.5821767969306242,
      "f_volume_turnover": null,
      "f_funding_rate": null,
      "f_tvl_mcap": null,
      "f_dev_activity": null,
      "f_onchain_activity": null,
      "f_narrative_heat": null,
      "f_market_cap_size": null,
      "composite_score": -0.2597
    },
    {
      "symbol": "OP",
      "price": 0.11839298910623265,
      "market_cap": null,
      "f_momentum_30d": -0.6047524972188547,
      "f_momentum_7d": -1.0,
      "f_ath_drawdown": -0.6718685208086098,
      "f_volume_turnover": null,
      "f_funding_rate": null,
      "f_tvl_mcap": null,
      "f_dev_activity": null,
      "f_onchain_activity": null,
      "f_narrative_heat": null,
      "f_market_cap_size": null,
      "composite_score": -0.4091
    }
  ],
  "_meta": {
    "source": "backfill",
    "synthetic": true,
    "n_factors": 3,
    "backfill_run": "2026-05-19T03:42:58.342783Z"
  }
}