{
  "timestamp": "2026-03-27T00:00:00+00:00",
  "date": "2026-03-27",
  "factor_weights": {
    "f_momentum_30d": 0.35,
    "f_momentum_7d": 0.25,
    "f_ath_drawdown": -0.2
  },
  "coins": [
    {
      "symbol": "APT",
      "price": 1.039150880259578,
      "market_cap": null,
      "f_momentum_30d": 0.2821630232314973,
      "f_momentum_7d": 0.18980825585088237,
      "f_ath_drawdown": -0.4716523398271367,
      "f_volume_turnover": null,
      "f_funding_rate": null,
      "f_tvl_mcap": null,
      "f_dev_activity": null,
      "f_onchain_activity": null,
      "f_narrative_heat": null,
      "f_market_cap_size": null,
      "composite_score": 0.3007
    },
    {
      "symbol": "RNDR",
      "price": 1.800678422696959,
      "market_cap": null,
      "f_momentum_30d": 0.3196481853387617,
      "f_momentum_7d": 0.14926288162701992,
      "f_ath_drawdown": -0.30835700903056773,
      "f_volume_turnover": null,
      "f_funding_rate": null,
      "f_tvl_mcap": null,
      "f_dev_activity": null,
      "f_onchain_activity": null,
      "f_narrative_heat": null,
      "f_market_cap_size": null,
      "composite_score": 0.2636
    },
    {
      "symbol": "XLM",
      "price": 0.17509252679479506,
      "market_cap": null,
      "f_momentum_30d": 0.166419374715284,
      "f_momentum_7d": 0.09803626359481238,
      "f_ath_drawdown": -0.238306416718023,
      "f_volume_turnover": null,
      "f_funding_rate": null,
      "f_tvl_mcap": null,
      "f_dev_activity": null,
      "f_onchain_activity": null,
      "f_narrative_heat": null,
      "f_market_cap_size": null,
      "composite_score": 0.163
    },
    {
      "symbol": "SUI",
      "price": 0.9513077965849,
      "market_cap": null,
      "f_momentum_30d": 0.10615501139210687,
      "f_momentum_7d": -0.12647985342111318,
      "f_ath_drawdown": -0.5100604432183925,
      "f_volume_turnover": null,
      "f_funding_rate": null,
      "f_tvl_mcap": null,
      "f_dev_activity": null,
      "f_onchain_activity": null,
      "f_narrative_heat": null,
      "f_market_cap_size": null,
      "composite_score": 0.1344
    },
    {
      "symbol": "SOL",
      "price": 90.7425040398005,
      "market_cap": null,
      "f_momentum_30d": 0.18109580266263395,
      "f_momentum_7d": -0.01415423496343512,
      "f_ath_drawdown": -0.2320815973173436,
      "f_volume_turnover": null,
      "f_funding_rate": null,
      "f_tvl_mcap": null,
      "f_dev_activity": null,
      "f_onchain_activity": null,
      "f_narrative_heat": null,
      "f_market_cap_size": null,
      "composite_score": 0.1328
    },
    {
      "symbol": "UNI",
      "price": 3.6656300044934618,
      "market_cap": null,
      "f_momentum_30d": 0.10261808195584134,
      "f_momentum_7d": -0.0324898435492856,
      "f_ath_drawdown": -0.3340042895017406,
      "f_volume_turnover": null,
      "f_funding_rate": null,
      "f_tvl_mcap": null,
      "f_dev_activity": null,
      "f_onchain_activity": null,
      "f_narrative_heat": null,
      "f_market_cap_size": null,
      "composite_score": 0.1182
    },
    {
      "symbol": "NEAR",
      "price": 1.256263980072964,
      "market_cap": null,
      "f_momentum_30d": 0.28738327104096123,
      "f_momentum_7d": -0.31313570982361594,
      "f_ath_drawdown": -0.3233164104896044,
      "f_volume_turnover": null,
      "f_funding_rate": null,
      "f_tvl_mcap": null,
      "f_dev_activity": null,
      "f_onchain_activity": null,
      "f_narrative_heat": null,
      "f_market_cap_size": null,
      "composite_score": 0.1087
    },
    {
      "symbol": "LDO",
      "price": 0.2964902309467231,
      "market_cap": null,
      "f_momentum_30d": -0.0005322836378005702,
      "f_momentum_7d": -0.09977044408809749,
      "f_ath_drawdown": -0.556359042605171,
      "f_volume_turnover": null,
      "f_funding_rate": null,
      "f_tvl_mcap": null,
      "f_dev_activity": null,
      "f_onchain_activity": null,
      "f_narrative_heat": null,
      "f_market_cap_size": null,
      "composite_score": 0.1077
    },
    {
      "symbol": "ETC",
      "price": 8.574708585137735,
      "market_cap": null,
      "f_momentum_30d": 0.04495985341927223,
      "f_momentum_7d": 0.006825791069436961,
      "f_ath_drawdown": -0.3331163224961925,
      "f_volume_turnover": null,
      "f_funding_rate": null,
      "f_tvl_mcap": null,
      "f_dev_activity": null,
      "f_onchain_activity": null,
      "f_narrative_heat": null,
      "f_market_cap_size": null,
      "composite_score": 0.1051
    },
    {
      "symbol": "ARB",
      "price": 0.09721917821528628,
      "market_cap": null,
      "f_momentum_30d": 0.04668782689120752,
      "f_momentum_7d": -0.18803365198817887,
      "f_ath_drawdown": -0.5626695395545913,
      "f_volume_turnover": null,
      "f_funding_rate": null,
      "f_tvl_mcap": null,
      "f_dev_activity": null,
      "f_onchain_activity": null,
      "f_narrative_heat": null,
      "f_market_cap_size": null,
      "composite_score": 0.1023
    },
    {
      "symbol": "LTC",
      "price": 55.85209257503228,
      "market_cap": null,
      "f_momentum_30d": 0.09475288093597484,
      "f_momentum_7d": -0.01606508327000334,
      "f_ath_drawdown": -0.25379826831533575,
      "f_volume_turnover": null,
      "f_funding_rate": null,
      "f_tvl_mcap": null,
      "f_dev_activity": null,
      "f_onchain_activity": null,
      "f_narrative_heat": null,
      "f_market_cap_size": null,
      "composite_score": 0.0999
    },
    {
      "symbol": "FIL",
      "price": 0.9100940650134824,
      "market_cap": null,
      "f_momentum_30d": 0.030382024241782265,
      "f_momentum_7d": -0.07277968194663492,
      "f_ath_drawdown": -0.42857687784070136,
      "f_volume_turnover": null,
      "f_funding_rate": null,
      "f_tvl_mcap": null,
      "f_dev_activity": null,
      "f_onchain_activity": null,
      "f_narrative_heat": null,
      "f_market_cap_size": null,
      "composite_score": 0.0977
    },
    {
      "symbol": "ETH",
      "price": 2149.8962047894333,
      "market_cap": null,
      "f_momentum_30d": 0.175163242325882,
      "f_momentum_7d": -0.10383760235321149,
      "f_ath_drawdown": -0.21366031840434305,
      "f_volume_turnover": null,
      "f_funding_rate": null,
      "f_tvl_mcap": null,
      "f_dev_activity": null,
      "f_onchain_activity": null,
      "f_narrative_heat": null,
      "f_market_cap_size": null,
      "composite_score": 0.0976
    },
    {
      "symbol": "LINK",
      "price": 9.242331477758245,
      "market_cap": null,
      "f_momentum_30d": 0.12782063165443752,
      "f_momentum_7d": -0.013891909389133986,
      "f_ath_drawdown": -0.1484257422857442,
      "f_volume_turnover": null,
      "f_funding_rate": null,
      "f_tvl_mcap": null,
      "f_dev_activity": null,
      "f_onchain_activity": null,
      "f_narrative_heat": null,
      "f_market_cap_size": null,
      "composite_score": 0.0887
    },
    {
      "symbol": "AVAX",
      "price": 9.558627832935064,
      "market_cap": null,
      "f_momentum_30d": 0.15236141063037703,
      "f_momentum_7d": -0.047049791996798776,
      "f_ath_drawdown": -0.12430629361639266,
      "f_volume_turnover": null,
      "f_funding_rate": null,
      "f_tvl_mcap": null,
      "f_dev_activity": null,
      "f_onchain_activity": null,
      "f_narrative_heat": null,
      "f_market_cap_size": null,
      "composite_score": 0.083
    },
    {
      "symbol": "TRX",
      "price": 0.313750885901253,
      "market_cap": null,
      "f_momentum_30d": 0.11314871635349179,
      "f_momentum_7d": 0.0976721679939995,
      "f_ath_drawdown": 0.0,
      "f_volume_turnover": null,
      "f_funding_rate": null,
      "f_tvl_mcap": null,
      "f_dev_activity": null,
      "f_onchain_activity": null,
      "f_narrative_heat": null,
      "f_market_cap_size": null,
      "composite_score": 0.08
    },
    {
      "symbol": "BTC",
      "price": 70789.76410868505,
      "market_cap": null,
      "f_momentum_30d": 0.11203918581935231,
      "f_momentum_7d": -0.02682187553055516,
      "f_ath_drawdown": -0.1571677566527085,
      "f_volume_turnover": null,
      "f_funding_rate": null,
      "f_tvl_mcap": null,
      "f_dev_activity": null,
      "f_onchain_activity": null,
      "f_narrative_heat": null,
      "f_market_cap_size": null,
      "composite_score": 0.0799
    },
    {
      "symbol": "BNB",
      "price": 641.9343428480702,
      "market_cap": null,
      "f_momentum_30d": 0.08249660819864953,
      "f_momentum_7d": -0.060589578218173394,
      "f_ath_drawdown": -0.2481767513617332,
      "f_volume_turnover": null,
      "f_funding_rate": null,
      "f_tvl_mcap": null,
      "f_dev_activity": null,
      "f_onchain_activity": null,
      "f_narrative_heat": null,
      "f_market_cap_size": null,
      "composite_score": 0.0792
    },
    {
      "symbol": "INJ",
      "price": 3.0329585387422764,
      "market_cap": null,
      "f_momentum_30d": -0.06509537399811743,
      "f_momentum_7d": -0.03308816122875144,
      "f_ath_drawdown": -0.461873977807116,
      "f_volume_turnover": null,
      "f_funding_rate": null,
      "f_tvl_mcap": null,
      "f_dev_activity": null,
      "f_onchain_activity": null,
      "f_narrative_heat": null,
      "f_market_cap_size": null,
      "composite_score": 0.0766
    },
    {
      "symbol": "BCH",
      "price": 470.45386902372974,
      "market_cap": null,
      "f_momentum_30d": -0.03233708287633771,
      "f_momentum_7d": 0.0891597119868674,
      "f_ath_drawdown": -0.21497189478036527,
      "f_volume_turnover": null,
      "f_funding_rate": null,
      "f_tvl_mcap": null,
      "f_dev_activity": null,
      "f_onchain_activity": null,
      "f_narrative_heat": null,
      "f_market_cap_size": null,
      "composite_score": 0.0675
    },
    {
      "symbol": "HBAR",
      "price": 0.09356429486244598,
      "market_cap": null,
      "f_momentum_30d": -0.004239701969504376,
      "f_momentum_7d": -0.08659583670194615,
      "f_ath_drawdown": -0.2907928272175703,
      "f_volume_turnover": null,
      "f_funding_rate": null,
      "f_tvl_mcap": null,
      "f_dev_activity": null,
      "f_onchain_activity": null,
      "f_narrative_heat": null,
      "f_market_cap_size": null,
      "composite_score": 0.0438
    },
    {
      "symbol": "DOGE",
      "price": 0.0943108740900728,
      "market_cap": null,
      "f_momentum_30d": 0.024701353568528386,
      "f_momentum_7d": -0.04779353587703291,
      "f_ath_drawdown": -0.18170139728875478,
      "f_volume_turnover": null,
      "f_funding_rate": null,
      "f_tvl_mcap": null,
      "f_dev_activity": null,
      "f_onchain_activity": null,
      "f_narrative_heat": null,
      "f_market_cap_size": null,
      "composite_score": 0.0413
    },
    {
      "symbol": "MKR",
      "price": 1708.587813620001,
      "market_cap": null,
      "f_momentum_30d": 0.16120613156874625,
      "f_momentum_7d": -0.22783387990460527,
      "f_ath_drawdown": -0.12431772403891844,
      "f_volume_turnover": null,
      "f_funding_rate": null,
      "f_tvl_mcap": null,
      "f_dev_activity": null,
      "f_onchain_activity": null,
      "f_narrative_heat": null,
      "f_market_cap_size": null,
      "composite_score": 0.0304
    },
    {
      "symbol": "OP",
      "price": 0.11185538567862038,
      "market_cap": null,
      "f_momentum_30d": -0.05521951491355753,
      "f_momentum_7d": -0.38424729463660945,
      "f_ath_drawdown": -0.6899877819174265,
      "f_volume_turnover": null,
      "f_funding_rate": null,
      "f_tvl_mcap": null,
      "f_dev_activity": null,
      "f_onchain_activity": null,
      "f_narrative_heat": null,
      "f_market_cap_size": null,
      "composite_score": 0.0283
    },
    {
      "symbol": "ADA",
      "price": 0.266072223079127,
      "market_cap": null,
      "f_momentum_30d": 0.02991195852206098,
      "f_momentum_7d": -0.11051969861428401,
      "f_ath_drawdown": -0.18133658981518824,
      "f_volume_turnover": null,
      "f_funding_rate": null,
      "f_tvl_mcap": null,
      "f_dev_activity": null,
      "f_onchain_activity": null,
      "f_narrative_heat": null,
      "f_market_cap_size": null,
      "composite_score": 0.0239
    },
    {
      "symbol": "AAVE",
      "price": 110.68755799421432,
      "market_cap": null,
      "f_momentum_30d": -0.01642424352320542,
      "f_momentum_7d": -0.2052212566787348,
      "f_ath_drawdown": -0.3773697338539071,
      "f_volume_turnover": null,
      "f_funding_rate": null,
      "f_tvl_mcap": null,
      "f_dev_activity": null,
      "f_onchain_activity": null,
      "f_narrative_heat": null,
      "f_market_cap_size": null,
      "composite_score": 0.023
    },
    {
      "symbol": "XRP",
      "price": 1.3982845908750596,
      "market_cap": null,
      "f_momentum_30d": 0.050909389661612625,
      "f_momentum_7d": -0.16770933322875042,
      "f_ath_drawdown": -0.20049541555103215,
      "f_volume_turnover": null,
      "f_funding_rate": null,
      "f_tvl_mcap": null,
      "f_dev_activity": null,
      "f_onchain_activity": null,
      "f_narrative_heat": null,
      "f_market_cap_size": null,
      "composite_score": 0.02
    },
    {
      "symbol": "DOT",
      "price": 1.3456138776035982,
      "market_cap": null,
      "f_momentum_30d": 0.07166338144272993,
      "f_momentum_7d": -0.4534098258830446,
      "f_ath_drawdown": -0.21042119663336992,
      "f_volume_turnover": null,
      "f_funding_rate": null,
      "f_tvl_mcap": null,
      "f_dev_activity": null,
      "f_onchain_activity": null,
      "f_narrative_heat": null,
      "f_market_cap_size": null,
      "composite_score": -0.0577
    },
    {
      "symbol": "ATOM",
      "price": 1.7425670762428642,
      "market_cap": null,
      "f_momentum_30d": -0.17248445745506213,
      "f_momentum_7d": -0.29837467918901983,
      "f_ath_drawdown": -0.31617576462944147,
      "f_volume_turnover": null,
      "f_funding_rate": null,
      "f_tvl_mcap": null,
      "f_dev_activity": null,
      "f_onchain_activity": null,
      "f_narrative_heat": null,
      "f_market_cap_size": null,
      "composite_score": -0.0897
    }
  ],
  "_meta": {
    "source": "backfill",
    "synthetic": true,
    "n_factors": 3,
    "backfill_run": "2026-05-19T03:42:58.416944Z"
  }
}