{
  "timestamp": "2026-05-22T00:00:00+00:00",
  "date": "2026-05-22",
  "factor_weights": {
    "f_momentum_30d": 0.35,
    "f_momentum_7d": 0.25,
    "f_ath_drawdown": -0.2
  },
  "coins": [
    {
      "symbol": "NEAR",
      "price": 1.7459405144927085,
      "market_cap": null,
      "f_momentum_30d": 0.27940453744578936,
      "f_momentum_7d": 0.39090040588386704,
      "f_ath_drawdown": 0.0,
      "f_volume_turnover": null,
      "f_funding_rate": null,
      "f_tvl_mcap": null,
      "f_dev_activity": null,
      "f_onchain_activity": null,
      "f_narrative_heat": null,
      "f_market_cap_size": null,
      "composite_score": 0.2444
    },
    {
      "symbol": "INJ",
      "price": 4.94047736824072,
      "market_cap": null,
      "f_momentum_30d": 0.5019851278077072,
      "f_momentum_7d": -0.10871617895240618,
      "f_ath_drawdown": -0.04410984633495127,
      "f_volume_turnover": null,
      "f_funding_rate": null,
      "f_tvl_mcap": null,
      "f_dev_activity": null,
      "f_onchain_activity": null,
      "f_narrative_heat": null,
      "f_market_cap_size": null,
      "composite_score": 0.1967
    },
    {
      "symbol": "ATOM",
      "price": 2.0693437894673554,
      "market_cap": null,
      "f_momentum_30d": 0.15620213725897852,
      "f_momentum_7d": 0.09306330803955849,
      "f_ath_drawdown": -0.1382855017622376,
      "f_volume_turnover": null,
      "f_funding_rate": null,
      "f_tvl_mcap": null,
      "f_dev_activity": null,
      "f_onchain_activity": null,
      "f_narrative_heat": null,
      "f_market_cap_size": null,
      "composite_score": 0.132
    },
    {
      "symbol": "UNI",
      "price": 3.6599003772596195,
      "market_cap": null,
      "f_momentum_30d": 0.1228817288907139,
      "f_momentum_7d": 0.044209959654623626,
      "f_ath_drawdown": -0.09880289626710184,
      "f_volume_turnover": null,
      "f_funding_rate": null,
      "f_tvl_mcap": null,
      "f_dev_activity": null,
      "f_onchain_activity": null,
      "f_narrative_heat": null,
      "f_market_cap_size": null,
      "composite_score": 0.0923
    },
    {
      "symbol": "RNDR",
      "price": 1.9319935749850272,
      "market_cap": null,
      "f_momentum_30d": 0.07751716476493968,
      "f_momentum_7d": 0.11700418402609546,
      "f_ath_drawdown": -0.06579700695405002,
      "f_volume_turnover": null,
      "f_funding_rate": null,
      "f_tvl_mcap": null,
      "f_dev_activity": null,
      "f_onchain_activity": null,
      "f_narrative_heat": null,
      "f_market_cap_size": null,
      "composite_score": 0.0869
    },
    {
      "symbol": "TRX",
      "price": 0.3602281579880286,
      "market_cap": null,
      "f_momentum_30d": 0.09588628875343494,
      "f_momentum_7d": 0.09219928873297178,
      "f_ath_drawdown": 0.0,
      "f_volume_turnover": null,
      "f_funding_rate": null,
      "f_tvl_mcap": null,
      "f_dev_activity": null,
      "f_onchain_activity": null,
      "f_narrative_heat": null,
      "f_market_cap_size": null,
      "composite_score": 0.0708
    },
    {
      "symbol": "FIL",
      "price": 0.9855923825417229,
      "market_cap": null,
      "f_momentum_30d": 0.06365855578000307,
      "f_momentum_7d": -0.1851341686711943,
      "f_ath_drawdown": -0.22426302260342526,
      "f_volume_turnover": null,
      "f_funding_rate": null,
      "f_tvl_mcap": null,
      "f_dev_activity": null,
      "f_onchain_activity": null,
      "f_narrative_heat": null,
      "f_market_cap_size": null,
      "composite_score": 0.0261
    },
    {
      "symbol": "ETC",
      "price": 9.014800968441072,
      "market_cap": null,
      "f_momentum_30d": 0.06934899170867637,
      "f_momentum_7d": -0.09073389627768197,
      "f_ath_drawdown": -0.0885441561816422,
      "f_volume_turnover": null,
      "f_funding_rate": null,
      "f_tvl_mcap": null,
      "f_dev_activity": null,
      "f_onchain_activity": null,
      "f_narrative_heat": null,
      "f_market_cap_size": null,
      "composite_score": 0.0241
    },
    {
      "symbol": "SUI",
      "price": 1.1133947921515486,
      "market_cap": null,
      "f_momentum_30d": 0.17417904608537374,
      "f_momentum_7d": -0.2803441555567087,
      "f_ath_drawdown": -0.13456574483366693,
      "f_volume_turnover": null,
      "f_funding_rate": null,
      "f_tvl_mcap": null,
      "f_dev_activity": null,
      "f_onchain_activity": null,
      "f_narrative_heat": null,
      "f_market_cap_size": null,
      "composite_score": 0.0222
    },
    {
      "symbol": "DOT",
      "price": 1.27109625151778,
      "market_cap": null,
      "f_momentum_30d": -0.006761807851140309,
      "f_momentum_7d": -0.15980673756242922,
      "f_ath_drawdown": -0.21953809758292375,
      "f_volume_turnover": null,
      "f_funding_rate": null,
      "f_tvl_mcap": null,
      "f_dev_activity": null,
      "f_onchain_activity": null,
      "f_narrative_heat": null,
      "f_market_cap_size": null,
      "composite_score": 0.002
    },
    {
      "symbol": "BNB",
      "price": 652.4752944107768,
      "market_cap": null,
      "f_momentum_30d": 0.03314384341204018,
      "f_momentum_7d": -0.086642812025141,
      "f_ath_drawdown": -0.04684427729183854,
      "f_volume_turnover": null,
      "f_funding_rate": null,
      "f_tvl_mcap": null,
      "f_dev_activity": null,
      "f_onchain_activity": null,
      "f_narrative_heat": null,
      "f_market_cap_size": null,
      "composite_score": -0.0009
    },
    {
      "symbol": "BTC",
      "price": 77778.33491784679,
      "market_cap": null,
      "f_momentum_30d": 0.025395227912053345,
      "f_momentum_7d": -0.08197241555443727,
      "f_ath_drawdown": -0.042597997595107594,
      "f_volume_turnover": null,
      "f_funding_rate": null,
      "f_tvl_mcap": null,
      "f_dev_activity": null,
      "f_onchain_activity": null,
      "f_narrative_heat": null,
      "f_market_cap_size": null,
      "composite_score": -0.0039
    },
    {
      "symbol": "DOGE",
      "price": 0.10558818629505093,
      "market_cap": null,
      "f_momentum_30d": 0.10639470554067781,
      "f_momentum_7d": -0.26380338486272603,
      "f_ath_drawdown": -0.08414575347437271,
      "f_volume_turnover": null,
      "f_funding_rate": null,
      "f_tvl_mcap": null,
      "f_dev_activity": null,
      "f_onchain_activity": null,
      "f_narrative_heat": null,
      "f_market_cap_size": null,
      "composite_score": -0.0149
    },
    {
      "symbol": "HBAR",
      "price": 0.08899211246100174,
      "market_cap": null,
      "f_momentum_30d": -0.008320678612160001,
      "f_momentum_7d": -0.15825179091673952,
      "f_ath_drawdown": -0.14684960299375027,
      "f_volume_turnover": null,
      "f_funding_rate": null,
      "f_tvl_mcap": null,
      "f_dev_activity": null,
      "f_onchain_activity": null,
      "f_narrative_heat": null,
      "f_market_cap_size": null,
      "composite_score": -0.0164
    },
    {
      "symbol": "LINK",
      "price": 9.694071163134137,
      "market_cap": null,
      "f_momentum_30d": 0.03708083063747449,
      "f_momentum_7d": -0.18536829970688884,
      "f_ath_drawdown": -0.08306454263177689,
      "f_volume_turnover": null,
      "f_funding_rate": null,
      "f_tvl_mcap": null,
      "f_dev_activity": null,
      "f_onchain_activity": null,
      "f_narrative_heat": null,
      "f_market_cap_size": null,
      "composite_score": -0.0209
    },
    {
      "symbol": "SOL",
      "price": 86.5378481575766,
      "market_cap": null,
      "f_momentum_30d": 0.009815721835779346,
      "f_momentum_7d": -0.1660486535334264,
      "f_ath_drawdown": -0.10480317331237551,
      "f_volume_turnover": null,
      "f_funding_rate": null,
      "f_tvl_mcap": null,
      "f_dev_activity": null,
      "f_onchain_activity": null,
      "f_narrative_heat": null,
      "f_market_cap_size": null,
      "composite_score": -0.0214
    },
    {
      "symbol": "AVAX",
      "price": 9.331398128465938,
      "market_cap": null,
      "f_momentum_30d": -0.004584617701963787,
      "f_momentum_7d": -0.1505074769518731,
      "f_ath_drawdown": -0.10736040720439366,
      "f_volume_turnover": null,
      "f_funding_rate": null,
      "f_tvl_mcap": null,
      "f_dev_activity": null,
      "f_onchain_activity": null,
      "f_narrative_heat": null,
      "f_market_cap_size": null,
      "composite_score": -0.0222
    },
    {
      "symbol": "ADA",
      "price": 0.24934284454348424,
      "market_cap": null,
      "f_momentum_30d": 0.0011462032102989277,
      "f_momentum_7d": -0.20467704889206872,
      "f_ath_drawdown": -0.15582753247936693,
      "f_volume_turnover": null,
      "f_funding_rate": null,
      "f_tvl_mcap": null,
      "f_dev_activity": null,
      "f_onchain_activity": null,
      "f_narrative_heat": null,
      "f_market_cap_size": null,
      "composite_score": -0.0245
    },
    {
      "symbol": "APT",
      "price": 0.960510026241521,
      "market_cap": null,
      "f_momentum_30d": 0.02611894124902097,
      "f_momentum_7d": -0.24358869741964576,
      "f_ath_drawdown": -0.15263018718850627,
      "f_volume_turnover": null,
      "f_funding_rate": null,
      "f_tvl_mcap": null,
      "f_dev_activity": null,
      "f_onchain_activity": null,
      "f_narrative_heat": null,
      "f_market_cap_size": null,
      "composite_score": -0.0265
    },
    {
      "symbol": "MKR",
      "price": 1646.3950630803874,
      "market_cap": null,
      "f_momentum_30d": -0.11179328513835486,
      "f_momentum_7d": -0.10341111146315704,
      "f_ath_drawdown": -0.20052463718818742,
      "f_volume_turnover": null,
      "f_funding_rate": null,
      "f_tvl_mcap": null,
      "f_dev_activity": null,
      "f_onchain_activity": null,
      "f_narrative_heat": null,
      "f_market_cap_size": null,
      "composite_score": -0.0311
    },
    {
      "symbol": "XRP",
      "price": 1.3747070406428938,
      "market_cap": null,
      "f_momentum_30d": -0.03935172847007987,
      "f_momentum_7d": -0.13520901773411437,
      "f_ath_drawdown": -0.10068043355041793,
      "f_volume_turnover": null,
      "f_funding_rate": null,
      "f_tvl_mcap": null,
      "f_dev_activity": null,
      "f_onchain_activity": null,
      "f_narrative_heat": null,
      "f_market_cap_size": null,
      "composite_score": -0.0343
    },
    {
      "symbol": "LTC",
      "price": 54.36195700714533,
      "market_cap": null,
      "f_momentum_30d": -0.012077837144448145,
      "f_momentum_7d": -0.16353340205730404,
      "f_ath_drawdown": -0.07690947912632388,
      "f_volume_turnover": null,
      "f_funding_rate": null,
      "f_tvl_mcap": null,
      "f_dev_activity": null,
      "f_onchain_activity": null,
      "f_narrative_heat": null,
      "f_market_cap_size": null,
      "composite_score": -0.0372
    },
    {
      "symbol": "LDO",
      "price": 0.3610030445104526,
      "market_cap": null,
      "f_momentum_30d": -0.03235819718853138,
      "f_momentum_7d": -0.20513938912972168,
      "f_ath_drawdown": -0.16253725626163554,
      "f_volume_turnover": null,
      "f_funding_rate": null,
      "f_tvl_mcap": null,
      "f_dev_activity": null,
      "f_onchain_activity": null,
      "f_narrative_heat": null,
      "f_market_cap_size": null,
      "composite_score": -0.0376
    },
    {
      "symbol": "OP",
      "price": 0.12963289296252578,
      "market_cap": null,
      "f_momentum_30d": 0.047083183962960205,
      "f_momentum_7d": -0.3813898017182057,
      "f_ath_drawdown": -0.2343775333930959,
      "f_volume_turnover": null,
      "f_funding_rate": null,
      "f_tvl_mcap": null,
      "f_dev_activity": null,
      "f_onchain_activity": null,
      "f_narrative_heat": null,
      "f_market_cap_size": null,
      "composite_score": -0.04
    },
    {
      "symbol": "AAVE",
      "price": 89.25814297805269,
      "market_cap": null,
      "f_momentum_30d": -0.06444454102277664,
      "f_momentum_7d": -0.26773643175769785,
      "f_ath_drawdown": -0.2837212265376754,
      "f_volume_turnover": null,
      "f_funding_rate": null,
      "f_tvl_mcap": null,
      "f_dev_activity": null,
      "f_onchain_activity": null,
      "f_narrative_heat": null,
      "f_market_cap_size": null,
      "composite_score": -0.0409
    },
    {
      "symbol": "ETH",
      "price": 2137.970987495836,
      "market_cap": null,
      "f_momentum_30d": -0.07649810211240764,
      "f_momentum_7d": -0.1866996208448365,
      "f_ath_drawdown": -0.1122018216417407,
      "f_volume_turnover": null,
      "f_funding_rate": null,
      "f_tvl_mcap": null,
      "f_dev_activity": null,
      "f_onchain_activity": null,
      "f_narrative_heat": null,
      "f_market_cap_size": null,
      "composite_score": -0.0638
    },
    {
      "symbol": "BCH",
      "price": 378.81273226850544,
      "market_cap": null,
      "f_momentum_30d": -0.14420698545897795,
      "f_momentum_7d": -0.426016752783528,
      "f_ath_drawdown": -0.3324076361665599,
      "f_volume_turnover": null,
      "f_funding_rate": null,
      "f_tvl_mcap": null,
      "f_dev_activity": null,
      "f_onchain_activity": null,
      "f_narrative_heat": null,
      "f_market_cap_size": null,
      "composite_score": -0.1131
    },
    {
      "symbol": "XLM",
      "price": 0.14574693738118885,
      "market_cap": null,
      "f_momentum_30d": -0.1714861687683048,
      "f_momentum_7d": -0.29073155827822483,
      "f_ath_drawdown": -0.19682004920842874,
      "f_volume_turnover": null,
      "f_funding_rate": null,
      "f_tvl_mcap": null,
      "f_dev_activity": null,
      "f_onchain_activity": null,
      "f_narrative_heat": null,
      "f_market_cap_size": null,
      "composite_score": -0.1167
    },
    {
      "symbol": "ARB",
      "price": 0.11197069736219516,
      "market_cap": null,
      "f_momentum_30d": -0.11366601200812292,
      "f_momentum_7d": -0.4636431937658207,
      "f_ath_drawdown": -0.22635065313440292,
      "f_volume_turnover": null,
      "f_funding_rate": null,
      "f_tvl_mcap": null,
      "f_dev_activity": null,
      "f_onchain_activity": null,
      "f_narrative_heat": null,
      "f_market_cap_size": null,
      "composite_score": -0.138
    }
  ],
  "_meta": {
    "source": "backfill",
    "synthetic": true,
    "n_factors": 3,
    "backfill_run": "2026-06-05T05:48:03.390842Z"
  }
}